remote_plot/__init__.py
remote_plot/client.py
remote_plot/server.py
remote_plot-1.2.1.dist-info/LICENSE
remote_plot-1.2.1.dist-info/METADATA
remote_plot-1.2.1.dist-info/WHEEL
remote_plot-1.2.1.dist-info/top_level.txt
remote_plot-1.2.1.dist-info/RECORD
