Metadata-Version: 2.1
Name: remote-plot
Version: 1.2.1
Summary: Like matplotlib but renders in a local server so you can work remotely
Home-page: https://github.com/itaicaspi/remote_plot
Author: Itai Caspi
Author-email: itaicaspi@gmail.com
License: UNKNOWN
Keywords: matplotlib,plotting,remote development
Platform: UNKNOWN
Classifier: Development Status :: 5 - Production/Stable
Classifier: Intended Audience :: Developers
Classifier: Topic :: Software Development :: Build Tools
Classifier: License :: OSI Approved :: MIT License
Classifier: Programming Language :: Python :: 3
Classifier: Programming Language :: Python :: 3.7
Classifier: Programming Language :: Python :: 3.8
Classifier: Programming Language :: Python :: 3.9
Classifier: Programming Language :: Python :: 3.10
Classifier: Programming Language :: Python :: 3 :: Only
Requires-Python: >=3.7, <4
License-File: LICENSE
Requires-Dist: pillow
Requires-Dist: numpy
Requires-Dist: matplotlib
Requires-Dist: requests
Provides-Extra: dev
Provides-Extra: test
